Metadata-Version: 2.1
Name: explainx
Version: 2.407
Summary: Explain and debug any black-box Machine Learning model.
Home-page: https://github.com/explainX/explainx
Author: explainx.ai
Author-email: muddassar@explainx.ai
License: MIT
Download-URL: https://github.com/explainX/explainx/archive/v2.403.zip
Keywords: Explainable AI,Explainable Machine Learning,trust,interpretability,transparent
Platform: UNKNOWN
Classifier: Development Status :: 3 - Alpha
Classifier: Intended Audience :: Developers
Classifier: Topic :: Software Development :: Build Tools
Classifier: License :: OSI Approved :: MIT License
Classifier: Programming Language :: Python :: 3
Classifier: Programming Language :: Python :: 3.4
Classifier: Programming Language :: Python :: 3.5
Classifier: Programming Language :: Python :: 3.6
